<?xml version="1.0" encoding="UTF-8"?>
<configuration>
    <include resource="org/springframework/boot/logging/logback/base.xml" />

    <springProfile name="production">
        <appender name="TadalinRollingFileAppender" class="ch.qos.logback.core.rolling.RollingFileAppender">
            <File>/tmp/tadalin.log</File>
            <rollingPolicy class="ch.qos.logback.core.rolling.TimeBasedRollingPolicy">
                <FileNamePattern>/tmp/tadalin.%d{yyyy-MM-dd}.log</FileNamePattern>
                <maxHistory>3000</maxHistory>
            </rollingPolicy>
            <encoder>
                <Pattern>%d{YYYY-MM-dd HH:mm:ss.SSS} [%thread] %-5level %logger{35} - %msg %n</Pattern>
            </encoder>
        </appender>
    </springProfile>

    <springProfile name="development">
        <root level="INFO">
            <appender-ref ref="CONSOLE" />
        </root>
    </springProfile>

    <springProfile name="production">
        <root level="INFO">
            <appender-ref ref="CONSOLE" />
            <appender-ref ref="TadalinRollingFileAppender" />
        </root>
    </springProfile>

    <logger name="${package}.mapper" level="DEBUG"/>

</configuration>